rlpe/__init__.py
rlpe/constants.py
rlpe/create_single_taxi_transforms.py
rlpe/experiments.py
rlpe/generate_specific_transformed_env.py
rlpe/main.py
rlpe/save_load_utils.py
rlpe/temp_taxi_example.py
rlpe/train_agent.py
rlpe/utils.py
rlpe/visualize.py
rlpe/Agents/__init__.py
rlpe/Agents/abstract_agent.py
rlpe/Agents/agent.py
rlpe/Agents/value_iteration_agent.py
rlpe/Agents/RL_agents/__init__.py
rlpe/Agents/RL_agents/cem_agents.py
rlpe/Agents/RL_agents/q_learning_agents.py
rlpe/Agents/RL_agents/rl_agent.py
rlpe/Agents/RL_agents/rllib_agents.py
rlpe/Agents/RL_agents/sarsa_agents.py
rlpe/Environments/__init__.py
rlpe/Environments/abstract_environment.py
rlpe/Environments/abstract_wrapper_env.py
rlpe/Environments/frozenlake_environment.py
rlpe/Environments/lunar_lander_wrapper.py
rlpe/Environments/speaker_listener_environment.py
rlpe/Environments/taxi_environment_wrapper.py
rlpe/Environments/ApplePicking/BiDict.py
rlpe/Environments/ApplePicking/__init__.py
rlpe/Environments/ApplePicking/apple_picking_constants.py
rlpe/Environments/ApplePicking/apple_picking_env.py
rlpe/Environments/LunarLander/__init__.py
rlpe/Environments/LunarLander/lunar_lander.py
rlpe/Environments/MultiTaxiEnv/__init__.py
rlpe/Environments/MultiTaxiEnv/multitaxienv/__init__.py
rlpe/Environments/MultiTaxiEnv/multitaxienv/config.py
rlpe/Environments/MultiTaxiEnv/multitaxienv/taxi_environment.py
rlpe/Environments/SingleTaxiEnv/__init__.py
rlpe/Environments/SingleTaxiEnv/single_small_taxi_env.py
rlpe/Environments/SingleTaxiEnv/single_taxi_constants.py
rlpe/Environments/SingleTaxiEnv/single_taxi_env.py
rlpe/Environments/SingleTaxiEnv/single_taxi_wrapper.py
rlpe/Observer/__init__.py
rlpe/Observer/abstract_expert.py
rlpe/Observer/anticipated_policy_generator.py
rlpe/Observer/lunar_lander_expert.py
rlpe/Observer/single_taxi_expert.py
rlpe/Observer/taxi_expert.py
rlpe/TransformSearch/__init__.py
rlpe/TransformSearch/anticipation_BFS.py
rlpe/TransformSearch/greedy_search.py
rlpe-0.0.1.dist-info/LICENSE
rlpe-0.0.1.dist-info/METADATA
rlpe-0.0.1.dist-info/WHEEL
rlpe-0.0.1.dist-info/top_level.txt
rlpe-0.0.1.dist-info/RECORD
