Metadata-Version: 2.1
Name: rlpe
Version: 0.0.1
Summary: Supplementary package for the paper "Reinforcement Learning Explainability via Model Transforms"
Home-page: https://github.com/MiraFinkel/marl_transforms.git
Author: Anonymous
Author-email: mirafinkel@gmail.com
License: UNKNOWN
Project-URL: Bug Tracker, https://github.com/MiraFinkel/marl_transforms.git
Platform: UNKNOWN
Classifier: Programming Language :: Python :: 3
Classifier: License :: OSI Approved :: MIT License
Classifier: Operating System :: OS Independent
Requires-Python: >=3.6
License-File: LICENSE
